test/__init__.py
autofunction-0.1.dist-info/METADATA
autofunction-0.1.dist-info/WHEEL
autofunction-0.1.dist-info/top_level.txt
autofunction-0.1.dist-info/RECORD
