Metadata-Version: 2.1
Name: autofunction
Version: 0.1
Summary: Some description
Home-page: 
Author: Daniel Reuter
Author-email: dreuter14@gmail.com
License: MIT
